coscontents/__init__.py
coscontents/api_utils.py
coscontents/chunks.py
coscontents/coscontents.py
coscontents/genericfs.py
coscontents/genericmanager.py
coscontents/hybridmanager.py
coscontents/s3_fs.py
coscontents-2023.1006.dist-info/LICENSE
coscontents-2023.1006.dist-info/METADATA
coscontents-2023.1006.dist-info/WHEEL
coscontents-2023.1006.dist-info/top_level.txt
coscontents-2023.1006.dist-info/RECORD
