Metadata-Version: 2.1
Name: coscontents
Version: 2023.1006
Summary: COS Contents Manage for storing Jupyterlab Notebooks in IBM Cloud Object Storage
Author-email: Gines Carrascal <gines_carrascal@es.ibm.com>
License: Apache License
Keywords: IBM,COS,cloud,jupyter,notebook
Classifier: Development Status :: 3 - Alpha
Classifier: License :: OSI Approved :: Apache Software License
Classifier: Programming Language :: Python
Classifier: Programming Language :: Python :: 3
Requires-Python: >=3.7.4
License-File: LICENSE
Requires-Dist: ibm-cos-sdk (>=2.13.0)
Requires-Dist: s3fs
Requires-Dist: jupyter-server
Requires-Dist: nbformat
Requires-Dist: tornado
Requires-Dist: traitlets
Provides-Extra: dev
Requires-Dist: black ; extra == 'dev'
Requires-Dist: bumpver ; extra == 'dev'
Requires-Dist: isort ; extra == 'dev'
Requires-Dist: pip-tools ; extra == 'dev'
Requires-Dist: pytest ; extra == 'dev'
